LICENSE
MANIFEST.in
README.md
setup.cfg
setup.py
admino/__init__.py
admino/constants.py
admino/fields.py
admino/forms.py
admino/serializers.py
admino/sites.py
admino/utils.py
admino/views.py
admino/templatetags/__init__.py
admino/templatetags/admino_tags.py
django_admino.egg-info/PKG-INFO
django_admino.egg-info/SOURCES.txt
django_admino.egg-info/dependency_links.txt
django_admino.egg-info/top_level.txt